pyppur/__init__.py
pyppur/examples/basic_usage.py
pyppur/examples/example.ipynb
pyppur/objectives/__init__.py
pyppur/objectives/base.py
pyppur/objectives/distance.py
pyppur/objectives/reconstruction.py
pyppur/optimizers/__init__.py
pyppur/optimizers/base.py
pyppur/optimizers/grid_optimizer.py
pyppur/optimizers/scipy_optimizer.py
pyppur/projection_pursuit.py
pyppur/utils/__init__.py
pyppur/utils/metrics.py
pyppur/utils/preprocessing.py
pyppur/utils/visualization.py
pyppur-0.4.0.dist-info/WHEEL
pyppur-0.4.0.dist-info/METADATA
pyppur-0.4.0.dist-info/RECORD
