Metadata-Version: 2.3
Name: pyppur
Version: 0.4.0
Summary: Advanced Projection Pursuit implementation with tied/untied weights, nonlinear/linear distance distortion, and comprehensive documentation
Author: Gaurav Sood
Author-email: Gaurav Sood <gsood07@gmail.com>
License: MIT License
Classifier: Development Status :: 4 - Beta
Classifier: Intended Audience :: Science/Research
Classifier: License :: OSI Approved :: MIT License
Classifier: Operating System :: OS Independent
Classifier: Programming Language :: Python :: 3
Classifier: Programming Language :: Python :: 3.11
Classifier: Programming Language :: Python :: 3.12
Classifier: Programming Language :: Python :: 3.13
Classifier: Topic :: Scientific/Engineering :: Artificial Intelligence
Classifier: Topic :: Scientific/Engineering :: Information Analysis
Classifier: Topic :: Scientific/Engineering :: Mathematics
Requires-Dist: numpy>=1.20.0
Requires-Dist: scipy>=1.7.0
Requires-Dist: scikit-learn>=1.0.0
Requires-Dist: matplotlib>=3.3.0
Requires-Dist: sphinx>=7.0 ; extra == 'docs'
Requires-Dist: furo>=2024.1.29 ; extra == 'docs'
Requires-Dist: sphinx-autodoc-typehints>=1.25 ; extra == 'docs'
Requires-Dist: sphinx-copybutton>=0.5 ; extra == 'docs'
Requires-Dist: myst-parser>=2.0 ; extra == 'docs'
Requires-Python: >=3.11
Project-URL: Bug Tracker, https://github.com/gojiplus/pyppur/issues
Project-URL: Homepage, https://github.com/gojiplus/pyppur
Provides-Extra: docs
